Workbook

Sheet Balance_raw
B1: Treasury Shares Number | C1: Ordinary Shares Number | D1: Share Issued | E1: Net Debt | F1: Total Debt | G1: Tangible Book Value | H1: Invested Capital | I1: Working Capital | J1: Net Tangible Assets | K1: Capital Lease Obligations | L1: Common Stock Equity | M1: Total Capitalization | N1: Total Equity Gross Minority Interest | O1: Stockholders Equity | P1: Gains Losses Not Affecting Retained Earnings | Q1: Other Equity Adjustments | R1: Retained Earnings | S1: Capital Stock | T1: Common Stock | U1: Total Liabilities Net Minority Interest | V1: Total Non Current Liabilities Net Minority Interest | W1: Other Non Current Liabilities | X1: Tradeand Other Payables Non Current | Y1: Long Term Debt And Capital Lease Obligation | Z1: Long Term Capital Lease Obligation | AA1: Long Term Debt | AB1: Current Liabilities | AC1: Other Current Liabilities | AD1: Current Deferred Liabilities | AE1: Current Deferred Revenue | AF1: Current Debt And Capital Lease Obligation | AG1: Current Capital Lease Obligation | AH1: Current Debt | AI1: Other Current Borrowings | AJ1: Commercial Paper | AK1: Payables And Accrued Expenses | AL1: Current Accrued Expenses | AM1: Payables | AN1: Total Tax Payable | AO1: Income Tax Payable | AP1: Accounts Payable | AQ1: Total Assets | AR1: Total Non Current Assets | AS1: Other Non Current Assets | AT1: Non Current Deferred Assets | AU1: Non Current Deferred Taxes Assets | AV1: Investments And Advances | AW1: Other Investments | AX1: Investmentin Financial Assets | AY1: Available For Sale Securities | AZ1: Net PPE | BA1: Accumulated Depreciation | BB1: Gross PPE | BC1: Leases | BD1: Other Properties | BE1: Machinery Furniture Equipment | BF1: Land And Improvements | BG1: Properties | BH1: Current Assets | BI1: Other Current Assets | BJ1: Inventory | BK1: Receivables | BL1: Other Receivables | BM1: Accounts Receivable | BN1: Cash Cash Equivalents And Short Term Investments | BO1: Other Short Term Investments | BP1: Cash And Cash Equivalents | BQ1: Cash Equivalents | BR1: Cash Financial | BS1: Short Term Debt
A2: 45930 | C2: 14773260000 | D2: 14773260000 | E2: 62723000000 | F2: 98657000000 | G2: 73733000000 | H2: 172390000000 | I2: -17674000000 | J2: 73733000000 | L2: 73733000000 | M2: 152061000000 | N2: 73733000000 | O2: 73733000000 | P2: -5571000000 | Q2: -5571000000 | R2: -14264000000 | S2: 93568000000 | T2: 93568000000 | U2: 285508000000 | V2: 119877000000 | W2: 41549000000 | Y2: 78328000000 | AA2: 78328000000 | AB2: 165631000000 | AC2: 44452000000 | AD2: 9055000000 | AE2: 9055000000 | AF2: 20329000000 | AH2: 20329000000 | AI2: 12350000000 | AJ2: 7979000000 | AK2: 91795000000 | AL2: 8919000000 | AM2: 82876000000 | AN2: 13016000000 | AO2: 13016000000 | AP2: 69860000000 | AQ2: 359241000000 | AR2: 211284000000 | AS2: 62950000000 | AT2: 20777000000 | AU2: 20777000000 | AV2: 77723000000 | AX2: 77723000000 | AY2: 77723000000 | AZ2: 49834000000 | BA2: -76014000000 | BB2: 125848000000 | BC2: 15091000000 | BE2: 83420000000 | BF2: 27337000000 | BG2: 0 | BH2: 147957000000 | BI2: 14585000000 | BJ2: 5718000000 | BK2: 72957000000 | BL2: 33180000000 | BM2: 39777000000 | BN2: 54697000000 | BO2: 18763000000 | BP2: 35934000000 | BQ2: 7667000000 | BR2: 28267000000 | BS2: =F2-AA2 -> 20329000000
A3: 45565 | C3: 15116786000 | D3: 15116786000 | E3: 76686000000 | F3: 106629000000 | G3: 56950000000 | H3: 163579000000 | I3: -23405000000 | J3: 56950000000 | L3: 56950000000 | M3: 142700000000 | N3: 56950000000 | O3: 56950000000 | P3: -7172000000 | Q3: -7172000000 | R3: -19154000000 | S3: 83276000000 | T3: 83276000000 | U3: 308030000000 | V3: 131638000000 | W3: 45888000000 | X3: 9254000000 | Y3: 85750000000 | AA3: 85750000000 | AB3: 176392000000 | AC3: 44024000000 | AD3: 8249000000 | AE3: 8249000000 | AF3: 20879000000 | AH3: 20879000000 | AI3: 10912000000 | AJ3: 9967000000 | AK3: 103240000000 | AL3: =AK3-AM3 -> 7679000000 | AM3: 95561000000 | AN3: 26601000000 | AO3: 26601000000 | AP3: 68960000000 | AQ3: 364980000000 | AR3: 211993000000 | AS3: 55335000000 | AT3: 19499000000 | AU3: 19499000000 | AV3: 91479000000 | AX3: 91479000000 | AY3: 91479000000 | AZ3: 45680000000 | BA3: -73448000000 | BB3: 119128000000 | BC3: 14233000000 | BE3: 80205000000 | BF3: 24690000000 | BG3: 0 | BH3: 152987000000 | BI3: 14287000000 | BJ3: 7286000000 | BK3: 66243000000 | BL3: 32833000000 | BM3: 33410000000 | BN3: 65171000000 | BO3: 35228000000 | BP3: 29943000000 | BQ3: 2744000000 | BR3: 27199000000 | BS3: =F3-AA3 -> 20879000000
A4: 45199 | B4: 0 | C4: 15550061000 | D4: 15550061000 | E4: 81123000000 | F4: 111088000000 | G4: 62146000000 | H4: 173234000000 | I4: -1742000000 | J4: 62146000000 | K4: 12842000000 | L4: 62146000000 | M4: 157427000000 | N4: 62146000000 | O4: 62146000000 | P4: -11452000000 | Q4: -11452000000 | R4: -214000000 | S4: 73812000000 | T4: 73812000000 | U4: 290437000000 | V4: 145129000000 | W4: 34391000000 | X4: 15457000000 | Y4: 95281000000 | Z4: 11267000000 | AA4: 95281000000 | AB4: 145308000000 | AC4: 50010000000 | AD4: 8061000000 | AE4: 8061000000 | AF4: 15807000000 | AG4: 1575000000 | AH4: 15807000000 | AI4: 9822000000 | AJ4: 5985000000 | AK4: 71430000000 | AL4: =AK4-AM4 -> 0 | AM4: 71430000000 | AN4: 8819000000 | AO4: 8819000000 | AP4: 62611000000 | AQ4: 352583000000 | AR4: 209017000000 | AS4: 46906000000 | AT4: 17852000000 | AU4: 17852000000 | AV4: 100544000000 | AX4: 100544000000 | AY4: 100544000000 | AZ4: 43715000000 | BA4: -70884000000 | BB4: 114599000000 | BC4: 12839000000 | BD4: 10661000000 | BE4: 78314000000 | BF4: 23446000000 | BG4: 0 | BH4: 143566000000 | BI4: 14695000000 | BJ4: 6331000000 | BK4: 60985000000 | BL4: 31477000000 | BM4: 29508000000 | BN4: 61555000000 | BO4: 31590000000 | BP4: 29965000000 | BQ4: 1606000000 | BR4: 28359000000 | BS4: =F4-AA4 -> 15807000000
A5: 44834 | C5: 15943425000 | D5: 15943425000 | E5: 96423000000 | F5: 132480000000 | G5: 50672000000 | H5: 170741000000 | I5: -18577000000 | J5: 50672000000 | K5: 12411000000 | L5: 50672000000 | M5: 149631000000 | N5: 50672000000 | O5: 50672000000 | P5: -11109000000 | Q5: -11109000000 | R5: -3068000000 | S5: 64849000000 | T5: 64849000000 | U5: 302083000000 | V5: 148101000000 | W5: 21737000000 | X5: 16657000000 | Y5: 109707000000 | Z5: 10748000000 | AA5: 98959000000 | AB5: 153982000000 | AC5: 52630000000 | AD5: 7912000000 | AE5: 7912000000 | AF5: 22773000000 | AG5: 1663000000 | AH5: 21110000000 | AI5: 11128000000 | AJ5: 9982000000 | AK5: 70667000000 | AL5: =AK5-AM5 -> 0 | AM5: 70667000000 | AN5: 6552000000 | AO5: 6552000000 | AP5: 64115000000 | AQ5: 352755000000 | AR5: 217350000000 | AS5: 39053000000 | AT5: 15375000000 | AU5: 15375000000 | AV5: 120805000000 | AW5: 120805000000 | AX5: 120805000000 | AY5: 120805000000 | AZ5: 42117000000 | BA5: -72340000000 | BB5: 114457000000 | BC5: 11271000000 | BD5: 10417000000 | BE5: 81060000000 | BF5: 22126000000 | BG5: 0 | BH5: 135405000000 | BI5: 21223000000 | BJ5: 4946000000 | BK5: 60932000000 | BL5: 32748000000 | BM5: 28184000000 | BN5: 48304000000 | BO5: 24658000000 | BP5: 23646000000 | BQ5: 5100000000 | BR5: 18546000000 | BS5: =F5-AA5 -> 33521000000
A6: 44469 | K6: 11803000000 | X6: 24689000000 | Z6: 10275000000 | AG6: 1528000000 | AW6: 127877000000 | BD6: 10087000000

Sheet Cashflow_raw
B1: Free Cash Flow | C1: Repurchase Of Capital Stock | D1: Repayment Of Debt | E1: Issuance Of Debt | F1: Issuance Of Capital Stock | G1: Capital Expenditure | H1: Interest Paid Supplemental Data | I1: Income Tax Paid Supplemental Data | J1: End Cash Position | K1: Beginning Cash Position | L1: Changes In Cash | M1: Financing Cash Flow | N1: Cash Flow From Continuing Financing Activities | O1: Net Other Financing Charges | P1: Cash Dividends Paid | Q1: Common Stock Dividend Paid | R1: Net Common Stock Issuance | S1: Common Stock Payments | T1: Common Stock Issuance | U1: Net Issuance Payments Of Debt | V1: Net Short Term Debt Issuance | W1: Net Long Term Debt Issuance | X1: Long Term Debt Payments | Y1: Long Term Debt Issuance | Z1: Investing Cash Flow | AA1: Cash Flow From Continuing Investing Activities | AB1: Net Other Investing Changes | AC1: Net Investment Purchase And Sale | AD1: Sale Of Investment | AE1: Purchase Of Investment | AF1: Net Business Purchase And Sale | AG1: Purchase Of Business | AH1: Net PPE Purchase And Sale | AI1: Purchase Of PPE | AJ1: Operating Cash Flow | AK1: Cash Flow From Continuing Operating Activities | AL1: Change In Working Capital | AM1: Change In Other Working Capital | AN1: Change In Other Current Liabilities | AO1: Change In Other Current Assets | AP1: Change In Payables And Accrued Expense | AQ1: Change In Payable | AR1: Change In Account Payable | AS1: Change In Inventory | AT1: Change In Receivables | AU1: Changes In Account Receivables | AV1: Other Non Cash Items | AW1: Stock Based Compensation | AX1: Deferred Tax | AY1: Deferred Income Tax | AZ1: Depreciation Amortization Depletion | BA1: Depreciation And Amortization | BB1: Net Income From Continuing Operations
A2: 45930 | B2: 98767000000 | C2: -90711000000 | D2: -10932000000 | E2: 4481000000 | G2: -12715000000 | I2: 43369000000 | J2: 35934000000 | K2: 29943000000 | L2: 5991000000 | M2: -120686000000 | N2: -120686000000 | O2: -6071000000 | P2: -15421000000 | Q2: -15421000000 | R2: -90711000000 | S2: -90711000000 | U2: -8483000000 | V2: -2032000000 | W2: -6451000000 | X2: -10932000000 | Y2: 4481000000 | Z2: 15195000000 | AA2: 15195000000 | AB2: -1480000000 | AC2: 29390000000 | AD2: 53797000000 | AE2: -24407000000 | AH2: -12715000000 | AI2: -12715000000 | AJ2: 111482000000 | AK2: 111482000000 | AL2: -25000000000 | AN2: -11076000000 | AO2: -9197000000 | AP2: 902000000 | AQ2: 902000000 | AR2: 902000000 | AS2: 1400000000 | AT2: -7029000000 | AU2: -6682000000 | AV2: -89000000 | AW2: 12863000000 | AZ2: 11698000000 | BA2: 11698000000 | BB2: 112010000000
A3: 45565 | B3: 108807000000 | C3: -94949000000 | D3: -9958000000 | E3: 0 | G3: -9447000000 | I3: 26102000000 | J3: 29943000000 | K3: 30737000000 | L3: -794000000 | M3: -121983000000 | N3: -121983000000 | O3: -5802000000 | P3: -15234000000 | Q3: -15234000000 | R3: -94949000000 | S3: -94949000000 | U3: -5998000000 | V3: 3960000000 | W3: -9958000000 | X3: -9958000000 | Y3: 0 | Z3: 2935000000 | AA3: 2935000000 | AB3: -1308000000 | AC3: 13690000000 | AD3: 62346000000 | AE3: -48656000000 | AH3: -9447000000 | AI3: -9447000000 | AJ3: 118254000000 | AK3: 118254000000 | AL3: 3651000000 | AN3: 15552000000 | AO3: -11731000000 | AP3: 6020000000 | AQ3: 6020000000 | AR3: 6020000000 | AS3: -1046000000 | AT3: -5144000000 | AU3: -3788000000 | AV3: -2266000000 | AW3: 11688000000 | AZ3: 11445000000 | BA3: 11445000000 | BB3: 93736000000
A4: 45199 | B4: 99584000000 | C4: -77550000000 | D4: -11151000000 | E4: 5228000000 | G4: -10959000000 | H4: 3803000000 | I4: 18679000000 | J4: 30737000000 | K4: 24977000000 | L4: 5760000000 | M4: -108488000000 | N4: -108488000000 | O4: -6012000000 | P4: -15025000000 | Q4: -15025000000 | R4: -77550000000 | S4: -77550000000 | U4: -9901000000 | V4: -3978000000 | W4: -5923000000 | X4: -11151000000 | Y4: 5228000000 | Z4: 3705000000 | AA4: 3705000000 | AB4: -1337000000 | AC4: 16001000000 | AD4: 45514000000 | AE4: -29513000000 | AH4: -10959000000 | AI4: -10959000000 | AJ4: 110543000000 | AK4: 110543000000 | AL4: -6577000000 | AN4: 3031000000 | AO4: -5684000000 | AP4: -1889000000 | AQ4: -1889000000 | AR4: -1889000000 | AS4: -1618000000 | AT4: -417000000 | AU4: -1688000000 | AV4: -2227000000 | AW4: 10833000000 | AZ4: 11519000000 | BA4: 11519000000 | BB4: 96995000000
A5: 44834 | B5: 111443000000 | C5: -89402000000 | D5: -9543000000 | E5: 5465000000 | G5: -10708000000 | H5: 2865000000 | I5: 19573000000 | J5: 24977000000 | K5: 35929000000 | L5: -10952000000 | M5: -110749000000 | N5: -110749000000 | O5: -6383000000 | P5: -14841000000 | Q5: -14841000000 | R5: -89402000000 | S5: -89402000000 | U5: -123000000 | V5: 3955000000 | W5: -4078000000 | X5: -9543000000 | Y5: 5465000000 | Z5: -22354000000 | AA5: -22354000000 | AB5: -2086000000 | AC5: -9560000000 | AD5: 67363000000 | AE5: -76923000000 | AF5: -306000000 | AG5: -306000000 | AH5: -10708000000 | AI5: -10708000000 | AJ5: 122151000000 | AK5: 122151000000 | AL5: 1200000000 | AM5: 478000000 | AN5: 6110000000 | AO5: -6499000000 | AP5: 9448000000 | AQ5: 9448000000 | AR5: 9448000000 | AS5: 1484000000 | AT5: -9343000000 | AU5: -1823000000 | AV5: 1006000000 | AW5: 9038000000 | AX5: 895000000 | AY5: 895000000 | AZ5: 11104000000 | BA5: 11104000000 | BB5: 99803000000

Sheet Income_raw
B1: Tax Effect Of Unusual Items | C1: Tax Rate For Calcs | D1: Normalized EBITDA | E1: Net Income From Continuing Operation Net Minority Interest | F1: Reconciled Depreciation | G1: Reconciled Cost Of Revenue | H1: EBITDA | I1: EBIT | J1: Net Interest Income | K1: Interest Expense | L1: Interest Income | M1: Normalized Income | N1: Net Income From Continuing And Discontinued Operation | O1: Total Expenses | P1: Total Operating Income As Reported | Q1: Diluted Average Shares | R1: Basic Average Shares | S1: Diluted EPS | T1: Basic EPS | U1: Diluted NI Availto Com Stockholders | V1: Net Income Common Stockholders | W1: Net Income | X1: Net Income Including Noncontrolling Interests | Y1: Net Income Continuous Operations | Z1: Tax Provision | AA1: Pretax Income | AB1: Other Income Expense | AC1: Other Non Operating Income Expenses | AD1: Net Non Operating Interest Income Expense | AE1: Interest Expense Non Operating | AF1: Interest Income Non Operating | AG1: Operating Income | AH1: Operating Expense | AI1: Research And Development | AJ1: Selling General And Administration | AK1: Gross Profit | AL1: Cost Of Revenue | AM1: Total Revenue | AN1: Operating Revenue
A2: 45930 | B2: 0 | C2: 0.156 | D2: 144748000000 | E2: 112010000000 | F2: 11698000000 | G2: 220960000000 | H2: 144748000000 | I2: 133050000000 | K2: =I2-AA2 -> 321000000 | M2: 112010000000 | N2: 112010000000 | O2: 283111000000 | P2: 133050000000 | Q2: 15004697000 | R2: 14948500000 | S2: 7.46 | T2: 7.49 | U2: 112010000000 | V2: 112010000000 | W2: 112010000000 | X2: 112010000000 | Y2: 112010000000 | Z2: 20719000000 | AA2: 132729000000 | AB2: -321000000 | AC2: -321000000 | AG2: 133050000000 | AH2: 62151000000 | AI2: 34550000000 | AJ2: 27601000000 | AK2: 195201000000 | AL2: 220960000000 | AM2: 416161000000 | AN2: 416161000000
A3: 45565 | B3: 0 | C3: 0.241 | D3: 134661000000 | E3: 93736000000 | F3: 11445000000 | G3: 210352000000 | H3: 134661000000 | I3: 123216000000 | M3: 93736000000 | N3: 93736000000 | O3: 267819000000 | P3: 123216000000 | Q3: 15408095000 | R3: 15343783000 | S3: 6.08 | T3: 6.11 | U3: 93736000000 | V3: 93736000000 | W3: 93736000000 | X3: 93736000000 | Y3: 93736000000 | Z3: 29749000000 | AA3: 123485000000 | AB3: 269000000 | AC3: 269000000 | AG3: 123216000000 | AH3: 57467000000 | AI3: 31370000000 | AJ3: 26097000000 | AK3: 180683000000 | AL3: 210352000000 | AM3: 391035000000 | AN3: 391035000000
A4: 45199 | B4: 0 | C4: 0.147 | D4: 125820000000 | E4: 96995000000 | F4: 11519000000 | G4: 214137000000 | H4: 125820000000 | I4: 114301000000 | J4: -183000000 | K4: 3933000000 | L4: 3750000000 | M4: 96995000000 | N4: 96995000000 | O4: 268984000000 | P4: 114301000000 | Q4: 15812547000 | R4: 15744231000 | S4: 6.13 | T4: 6.16 | U4: 96995000000 | V4: 96995000000 | W4: 96995000000 | X4: 96995000000 | Y4: 96995000000 | Z4: 16741000000 | AA4: 113736000000 | AB4: -565000000 | AC4: -565000000 | AD4: -183000000 | AE4: 3933000000 | AF4: 3750000000 | AG4: 114301000000 | AH4: 54847000000 | AI4: 29915000000 | AJ4: 24932000000 | AK4: 169148000000 | AL4: 214137000000 | AM4: 383285000000 | AN4: 383285000000
A5: 44834 | B5: 0 | C5: 0.162 | D5: 130541000000 | E5: 99803000000 | F5: 11104000000 | G5: 223546000000 | H5: 130541000000 | I5: 119437000000 | J5: -106000000 | K5: 2931000000 | L5: 2825000000 | M5: 99803000000 | N5: 99803000000 | O5: 274891000000 | P5: 119437000000 | Q5: 16325819000 | R5: 16215963000 | S5: 6.11 | T5: 6.15 | U5: 99803000000 | V5: 99803000000 | W5: 99803000000 | X5: 99803000000 | Y5: 99803000000 | Z5: 19300000000 | AA5: 119103000000 | AB5: -334000000 | AC5: -334000000 | AD5: -106000000 | AE5: 2931000000 | AF5: 2825000000 | AG5: 119437000000 | AH5: 51345000000 | AI5: 26251000000 | AJ5: 25094000000 | AK5: 170782000000 | AL5: 223546000000 | AM5: 394328000000 | AN5: 394328000000
A6: 44469 | J6: 198000000 | K6: 2645000000 | L6: 2843000000 | AD6: 198000000 | AE6: 2645000000 | AF6: 2843000000

Sheet Balance_clean
A1: Line Item | B1: 2022 | C1: 2023 | D1: 2024 | E1: 2025
A2: Cash & Cash Equivalents | B2: =Balance_raw!BP5 -> 23646000000 | C2: =Balance_raw!BP4 -> 29965000000 | D2: =Balance_raw!BP3 -> 29943000000 | E2: =Balance_raw!BP2 -> 35934000000
A3: Accounts Receivable | B3: =Balance_raw!BM5 -> 28184000000 | C3: =Balance_raw!BM4 -> 29508000000 | D3: =Balance_raw!BM3 -> 33410000000 | E3: =Balance_raw!BM2 -> 39777000000
A4: Inventory | B4: =Balance_raw!BJ5 -> 4946000000 | C4: =Balance_raw!BJ4 -> 6331000000 | D4: =Balance_raw!BJ3 -> 7286000000 | E4: =Balance_raw!BJ2 -> 5718000000
A5: Other Current Assets | B5: =Balance_raw!BI5 -> 21223000000 | C5: =Balance_raw!BI4 -> 14695000000 | D5: =Balance_raw!BI3 -> 14287000000 | E5: =Balance_raw!BI2 -> 14585000000
A6: Total Current Assets | B6: =SUM(B2:B5) -> 77999000000 | C6: =SUM(C2:C5) -> 80499000000 | D6: =SUM(D2:D5) -> 84926000000 | E6: =SUM(E2:E5) -> 96014000000
A8: Property, Plant & Equipment (Net) | B8: =Balance_raw!AZ5 -> 42117000000 | C8: =Balance_raw!AZ4 -> 43715000000 | D8: =Balance_raw!AZ3 -> 45680000000 | E8: =Balance_raw!AZ2 -> 49834000000
A9: Other Non-Current Assets | B9: =Balance_raw!AS5 -> 39053000000 | C9: =Balance_raw!AS4 -> 46906000000 | D9: =Balance_raw!AS3 -> 55335000000 | E9: =Balance_raw!AS2 -> 62950000000
A10: Total Non-Current Assets | B10: =SUM(B8:B9) -> 81170000000 | C10: =SUM(C8:C9) -> 90621000000 | D10: =SUM(D8:D9) -> 101015000000 | E10: =SUM(E8:E9) -> 112784000000
A12: Total Assets | B12: =B6+B10 -> 159169000000 | C12: =C6+C10 -> 171120000000 | D12: =D6+D10 -> 185941000000 | E12: =E6+E10 -> 208798000000
A14: Accounts Payable | B14: =Balance_raw!AP5 -> 64115000000 | C14: =Balance_raw!AP4 -> 62611000000 | D14: =Balance_raw!AP3 -> 68960000000 | E14: =Balance_raw!AP2 -> 69860000000
A15: Accrued Expenses | B15: =Balance_raw!AL5 -> 0 | C15: =Balance_raw!AL4 -> 0 | D15: =Balance_raw!AL3 -> 7679000000 | E15: =Balance_raw!AL2 -> 8919000000
A16: Short-Term Debt | B16: =Balance_raw!BS5 -> 33521000000 | C16: =Balance_raw!BS4 -> 15807000000 | D16: =Balance_raw!BS3 -> 20879000000 | E16: =Balance_raw!BS2 -> 20329000000
A17: Total Current Liabilities | B17: =SUM(B14:B16) -> 97636000000 | C17: =SUM(C14:C16) -> 78418000000 | D17: =SUM(D14:D16) -> 97518000000 | E17: =SUM(E14:E16) -> 99108000000
A19: Long-Term Debt | B19: =Balance_raw!AA5 -> 98959000000 | C19: =Balance_raw!AA4 -> 95281000000 | D19: =Balance_raw!AA3 -> 85750000000 | E19: =Balance_raw!AA2 -> 78328000000
A20: Other Non-Current Liabilities | B20: =Balance_raw!W5 -> 21737000000 | C20: =Balance_raw!W4 -> 34391000000 | D20: =Balance_raw!W3 -> 45888000000 | E20: =Balance_raw!W2 -> 41549000000
A21: Total Non-Current Liabilities | B21: =SUM(B19:B20) -> 120696000000 | C21: =SUM(C19:C20) -> 129672000000 | D21: =SUM(D19:D20) -> 131638000000 | E21: =SUM(E19:E20) -> 119877000000
A23: Total Liabilities | B23: =B17+B21 -> 218332000000 | C23: =C17+C21 -> 208090000000 | D23: =D17+D21 -> 229156000000 | E23: =E17+E21 -> 218985000000
A25: Common Stock | B25: =Balance_raw!L5 -> 50672000000 | C25: =Balance_raw!L4 -> 62146000000 | D25: =Balance_raw!L3 -> 56950000000 | E25: =Balance_raw!L2 -> 73733000000
A26: Retained Earnings | B26: =Balance_raw!R5 -> -3068000000 | C26: =Balance_raw!R4 -> -214000000 | D26: =Balance_raw!R3 -> -19154000000 | E26: =Balance_raw!R2 -> -14264000000
A27: Total Stockholders’ Equity | B27: =B12-B23 -> -59163000000 | C27: =C12-C23 -> -36970000000 | D27: =D12-D23 -> -43215000000 | E27: =E12-E23 -> -10187000000

Sheet Cashflow_clean
A1: Item | B1: 2022 | C1: 2023 | D1: 2024 | E1: 2025
A2: Cash Flow from Operating Activities
A3: Net Income | B3: =Cashflow_raw!BB5 -> 99803000000 | C3: =Cashflow_raw!BB4 -> 96995000000 | D3: =Cashflow_raw!BB3 -> 93736000000 | E3: =Cashflow_raw!BB2 -> 112010000000
A4: Depreciation & Amortization | B4: =Cashflow_raw!BA5 -> 11104000000 | C4: =Cashflow_raw!BA4 -> 11519000000 | D4: =Cashflow_raw!BA3 -> 11445000000 | E4: =Cashflow_raw!BA2 -> 11698000000
A5: Stock Compensation | B5: =Cashflow_raw!AW5 -> 9038000000 | C5: =Cashflow_raw!AW4 -> 10833000000 | D5: =Cashflow_raw!AW3 -> 11688000000 | E5: =Cashflow_raw!AW2 -> 12863000000
A6: ΔAccounts Receivable | B6: =Cashflow_raw!AU5 -> -1823000000 | C6: =Cashflow_raw!AU4 -> -1688000000 | D6: =Cashflow_raw!AU3 -> -3788000000 | E6: =Cashflow_raw!AU2 -> -6682000000
A7: ΔInventory | B7: =Cashflow_raw!AS5 -> 1484000000 | C7: =Cashflow_raw!AS4 -> -1618000000 | D7: =Cashflow_raw!AS3 -> -1046000000 | E7: =Cashflow_raw!AS2 -> 1400000000
A8: ΔAccounts Payable | B8: =Cashflow_raw!AR5 -> 9448000000 | C8: =Cashflow_raw!AR4 -> -1889000000 | D8: =Cashflow_raw!AR3 -> 6020000000 | E8: =Cashflow_raw!AR2 -> 902000000
A9: Net CFO | B9: =SUM(B3:B8) -> 129054000000 | C9: =SUM(C3:C8) -> 114152000000 | D9: =SUM(D3:D8) -> 118055000000 | E9: =SUM(E3:E8) -> 132191000000
A10: Cash Flow from Investing Activities
A11: CapEx | B11: =Cashflow_raw!G5 -> -10708000000 | C11: =Cashflow_raw!G4 -> -10959000000 | D11: =Cashflow_raw!G3 -> -9447000000 | E11: =Cashflow_raw!G2 -> -12715000000
A12: Asset Sales / Investments | B12: =Cashflow_raw!AD5 -> 67363000000 | C12: =Cashflow_raw!AD4 -> 45514000000 | D12: =Cashflow_raw!AD3 -> 62346000000 | E12: =Cashflow_raw!AD2 -> 53797000000
A13: Net CFI | B13: =SUM(B11:B12) -> 56655000000 | C13: =SUM(C11:C12) -> 34555000000 | D13: =SUM(D11:D12) -> 52899000000 | E13: =SUM(E11:E12) -> 41082000000
A14: Cash Flow from Financing Activities
A15: Debt Issued | B15: =Cashflow_raw!E5 -> 5465000000 | C15: =Cashflow_raw!E4 -> 5228000000 | D15: =Cashflow_raw!E3 -> 0 | E15: =Cashflow_raw!E2 -> 4481000000
A16: Debt Repaid | B16: =Cashflow_raw!D5 -> -9543000000 | C16: =Cashflow_raw!D4 -> -11151000000 | D16: =Cashflow_raw!D3 -> -9958000000 | E16: =Cashflow_raw!D2 -> -10932000000
A17: Dividends Paid | B17: =Cashflow_raw!P5 -> -14841000000 | C17: =Cashflow_raw!P4 -> -15025000000 | D17: =Cashflow_raw!P3 -> -15234000000 | E17: =Cashflow_raw!P2 -> -15421000000
A18: Stock Repurchased | B18: =Cashflow_raw!C5 -> -89402000000 | C18: =Cashflow_raw!C4 -> -77550000000 | D18: =Cashflow_raw!C3 -> -94949000000 | E18: =Cashflow_raw!C2 -> -90711000000
A19: Net CFF | B19: =SUM(B15:B18) -> -108321000000 | C19: =SUM(C15:C18) -> -98498000000 | D19: =SUM(D15:D18) -> -120141000000 | E19: =SUM(E15:E18) -> -112583000000
A20: Net Change in Cash | C20: =C22-C21 -> 6319000000 | D20: =D22-D21 -> -22000000 | E20: =E22-E21 -> 5991000000
A21: Beginning Cash | C21: =Balance_clean!B2 -> 23646000000 | D21: =Balance_clean!C2 -> 29965000000 | E21: =Balance_clean!D2 -> 29943000000
A22: Ending Cash | B22: =Balance_clean!B2 -> 23646000000 | C22: =Balance_clean!C2 -> 29965000000 | D22: =Balance_clean!D2 -> 29943000000 | E22: =Balance_clean!E2 -> 35934000000

Sheet Income_clean
A1: Item | B1: 2022 | C1: 2023 | D1: 2024 | E1: 2025
A2: Revenue | B2: =Income_raw!AM5 -> 394328000000 | C2: =Income_raw!AM4 -> 383285000000 | D2: =Income_raw!AM3 -> 391035000000 | E2: =Income_raw!AM2 -> 416161000000
A3: Cost of Goods Sold (COGS) | B3: =Income_raw!AL5 -> 223546000000 | C3: =Income_raw!AL4 -> 214137000000 | D3: =Income_raw!AL3 -> 210352000000 | E3: =Income_raw!AL2 -> 220960000000
A4: Gross Profit | B4: =Income_raw!AK5 -> 170782000000 | C4: =Income_raw!AK4 -> 169148000000 | D4: =Income_raw!AK3 -> 180683000000 | E4: =Income_raw!AK2 -> 195201000000
A6: Operating Expenses:
A7: Selling General & Administrative Expenses | B7: =Income_raw!AJ5 -> 25094000000 | C7: =Income_raw!AJ4 -> 24932000000 | D7: =Income_raw!AJ3 -> 26097000000 | E7: =Income_raw!AJ2 -> 27601000000
A9: Total Operating Expenses | B9: =B7 -> 25094000000 | C9: =C7 -> 24932000000 | D9: =D7 -> 26097000000 | E9: =E7 -> 27601000000
A11: Operating Income | B11: =Income_raw!AG5 -> 119437000000 | C11: =Income_raw!AG4 -> 114301000000 | D11: =Income_raw!AG3 -> 123216000000 | E11: =Income_raw!AG2 -> 133050000000
A13: Other Income/Expenses:
A14: Interest Expense | B14: =Income_raw!K5 -> 2931000000 | C14: =Income_raw!K4 -> 3933000000
A15: Other Income | B15: =Income_raw!AB5 -> -334000000 | C15: =Income_raw!AB4 -> -565000000 | D15: =Income_raw!AB3 -> 269000000 | E15: =Income_raw!AB2 -> -321000000
A16: Total Other Income/Expenses | B16: =SUM(B14:B15) -> 2597000000 | C16: =SUM(C14:C15) -> 3368000000 | D16: =SUM(D14:D15) -> 269000000 | E16: =SUM(E14:E15) -> -321000000
A18: Income Before Tax | B18: =Income_raw!AA5 -> 119103000000 | C18: =Income_raw!AA4 -> 113736000000 | D18: =Income_raw!AA3 -> 123485000000 | E18: =Income_raw!AA2 -> 132729000000
A19: Income Tax Expense | B19: =Income_raw!Z5 -> 19300000000 | C19: =Income_raw!Z4 -> 16741000000 | D19: =Income_raw!Z3 -> 29749000000 | E19: =Income_raw!Z2 -> 20719000000
A21: Net Income | B21: =Income_raw!W5 -> 99803000000 | C21: =Income_raw!W4 -> 96995000000 | D21: =Income_raw!W3 -> 93736000000 | E21: =Income_raw!W2 -> 112010000000

Sheet KPI
A1: KPI's | B1: 2022 | C1: 2023 | D1: 2024 | E1: 2025
A2: Revenue Growth | C2: =(Income_clean!C2-Income_clean!B2)/(Income_clean!B2) -> -0.028004605 | D2: =(Income_clean!D2-Income_clean!C2)/(Income_clean!C2) -> 0.020219941 | E2: =(Income_clean!E2-Income_clean!D2)/(Income_clean!D2) -> 0.064255118
A3: Gross Margin | B3: =(Income_clean!B2-Income_clean!B3)/(Income_clean!B2) -> 0.43309631 | C3: =(Income_clean!C2-Income_clean!C3)/(Income_clean!C2) -> 0.4413113 | D3: =(Income_clean!D2-Income_clean!D3)/(Income_clean!D2) -> 0.4620635 | E3: =(Income_clean!E2-Income_clean!E3)/(Income_clean!E2) -> 0.46905164
A4: Operating Margin | B4: =(Income_clean!B11)/(Income_clean!B2) -> 0.30288744 | C4: =(Income_clean!C11)/(Income_clean!C2) -> 0.29821412 | D4: =(Income_clean!D11)/(Income_clean!D2) -> 0.31510223 | E4: =(Income_clean!E11)/(Income_clean!E2) -> 0.319708
A5: Net Margin | B5: =(Income_clean!B21)/(Income_clean!B2) -> 0.25309641 | C5: =(Income_clean!C21)/(Income_clean!C2) -> 0.25306234 | D5: =(Income_clean!D21)/(Income_clean!D2) -> 0.23971256 | E5: =(Income_clean!E21)/(Income_clean!E2) -> 0.26915064
A6: Free Cash Flow | B6: =Cashflow_clean!B9-Cashflow_clean!B11 -> 139762000000 | C6: =Cashflow_clean!C9-Cashflow_clean!C11 -> 125111000000 | D6: =Cashflow_clean!D9-Cashflow_clean!D11 -> 127502000000 | E6: =Cashflow_clean!E9-Cashflow_clean!E11 -> 144906000000
A8: Metric | B8: Value
A9: Revenue CAGR | B9: -0.0038709949
A10: Free Cash Flow CAGR | B10: -0.039450635
A11: Average Free Cash Flow Margin | B11: 0.48195595

Sheet Forecast + Dynamic Dashboard
B1: 2025 | C1: 2026 | D1: 2027 | E1: 2028 | F1: 2029 | G1: 2030 | I1: Year | J1: Revenue | K1: Free Cash Flow
A2: Revenue | B2: =Income_clean!E2 -> 416161000000 | C2: =B2*1.05 -> 436969050000 | D2: =C2*1.05 -> 458817502500 | E2: =D2*1.05 -> 481758377625 | F2: =E2*1.05 -> 5.058463e+11 | G2: =F2*1.05 -> 5.3113861e+11 | I2: 2026 | J2: =C2 -> 436969050000 | K2: =C9 -> 152151300000
A3: COGS % | B3: =B4/B2 -> 0.53094836 | C3: =(Income_clean!E3)/(Income_clean!E2) -> 0.53094836 | D3: =D4/D2 -> 0.53094836 | E3: =E4/E2 -> 0.53094836 | F3: =F4/F2 -> 0.53094836 | G3: =G4/G2 -> 0.53094836 | I3: 2027 | J3: =D2 -> 458817502500 | K3: =D9 -> 159758865000
A4: COGS | B4: =Income_clean!E3 -> 220960000000 | C4: =C2*C3 -> 2.32008e+11 | D4: =D2*C3 -> 2.436084e+11 | E4: =E2*D3 -> 2.5578882e+11 | F4: =F2*E3 -> 2.6857826e+11 | G4: =G2*F3 -> 282007174050 | I4: 2028 | J4: =E2 -> 481758377625 | K4: =E9 -> 167746808250
A5: Gross Margin % | B5: =B6/B2 -> 0.46905164 | C5: =C6/C2 -> 0.46905164 | D5: =D6/D2 -> 0.46905164 | E5: =E6/E2 -> 0.46905164 | F5: =F6/F2 -> 0.46905164 | G5: =G6/G2 -> 0.46905164 | I5: 2029 | J5: =F2 -> 5.058463e+11 | K5: =F9 -> 1.7613415e+11
A6: Gross Profit | B6: =B2-B4 -> 195201000000 | C6: =C2-C4 -> 2.0496105e+11 | D6: =D2-D4 -> 2.152091e+11 | E6: =E2-E4 -> 2.2596956e+11 | F6: =F2-F4 -> 2.3726804e+11 | G6: =G2-G4 -> 2.4913144e+11 | I6: 2030 | J6: =G2 -> 5.3113861e+11 | K6: =G9 -> 1.8494086e+11
A7: Operating Income | B7: =Income_clean!E11 -> 133050000000 | C7: =C2*C8 -> 139702500000 | D7: =D2*D8 -> 146687625000 | E7: =E2*E8 -> 154022006250 | F7: =F2*F8 -> 1.6172311e+11 | G7: =G2*G8 -> 1.6980926e+11
A8: Operating Margin % | B8: =B7/B2 -> 0.319708 | C8: =B7/B2 -> 0.319708 | D8: =C7/C2 -> 0.319708 | E8: =D7/D2 -> 0.319708 | F8: =E7/E2 -> 0.319708 | G8: =F7/F2 -> 0.319708 | I8: Revenue | J8: =_xlfn.XLOOKUP($K$9,$I$2:$I$6,J2:J6) -> 5.058463e+11 | K8: Year
A9: FCF | B9: =KPI!E6 -> 144906000000 | C9: =C2*C10 -> 152151300000 | D9: =D2*D10 -> 159758865000 | E9: =E2*E10 -> 167746808250 | F9: =F2*F10 -> 1.7613415e+11 | G9: =G2*G10 -> 1.8494086e+11 | I9: Free Cash Flow | J9: =_xlfn.XLOOKUP($K$9,$I$2:$I$6,K2:K6) -> 1.7613415e+11 | K9: 2029
A10: FCF % | B10: =B9/B2 -> 0.34819697 | C10: =B9/B2 -> 0.34819697 | D10: =C9/C2 -> 0.34819697 | E10: =D9/D2 -> 0.34819697 | F10: =E9/E2 -> 0.34819697 | G10: =F9/F2 -> 0.34819697

Sheet Dashboard
